calculator/__init__.py
calculator/calculator.py
pip_install_test_20250106-0.3.0.dist-info/METADATA
pip_install_test_20250106-0.3.0.dist-info/WHEEL
pip_install_test_20250106-0.3.0.dist-info/RECORD
