Metadata-Version: 2.1
Name: pip-install-test-20250106
Version: 0.3.0
Summary: 
Author: Robertson Brinker
Author-email: robertsonbrinker@gmail.com
Requires-Python: >=3.12,<4.0
Classifier: Programming Language :: Python :: 3
Classifier: Programming Language :: Python :: 3.12
Classifier: Programming Language :: Python :: 3.13
